hyperscience/__init__.py
hyperscience/_version.py
hyperscience/api/__init__.py
hyperscience/api/api_controller.py
hyperscience/api/request_handler.py
hyperscience/api/model/__init__.py
hyperscience/api/model/http_verb.py
hyperscience/auth/__init__.py
hyperscience/auth/oauth.py
hyperscience/auth/model/__init__.py
hyperscience/auth/model/credentials.py
hyperscience/config/__init__.py
hyperscience/config/configuration.py
hyperscience/errors/__init__.py
hyperscience/errors/configuration_exceptions.py
hyperscience/utils/__init__.py
hyperscience/utils/logger.py
hyperscience/utils/singleton.py
samples/api/__init__.py
samples/api/api_sample.py
hyperscience_saas_client-1.0.10.dist-info/LICENSE.txt
hyperscience_saas_client-1.0.10.dist-info/METADATA
hyperscience_saas_client-1.0.10.dist-info/WHEEL
hyperscience_saas_client-1.0.10.dist-info/top_level.txt
hyperscience_saas_client-1.0.10.dist-info/RECORD
