Metadata-Version: 2.1
Name: hyperscience-saas-client
Version: 1.0.10
Summary: hyperscience saas client library
Home-page: UNKNOWN
Author: Hyperscience
License: Apache License 2.0
Platform: UNKNOWN
Requires-Python: >=3.6
License-File: LICENSE.txt
Requires-Dist: requests (>=2.24.0)
Requires-Dist: urllib3 (>=1.25.10)
